{
  "parameters": {
    "analysis_id": "dependency-monkey-210306093513-17a58dbd9d61f188"
  },
  "report": {
    "metadata": {
      "analyzer": "thoth-adviser",
      "analyzer_version": "0.25.1",
      "arguments": {
        "dependency-monkey": {
          "beam_width": 1000000,
          "context": "input/context.json",
          "count": 1,
          "decision_type": "all",
          "dev": false,
          "dry_run": false,
          "library_usage": null,
          "limit_latest_versions": 9999999,
          "no_pretty": false,
          "pipeline": "input/pipeline.json",
          "plot": null,
          "predictor": "RandomWalk",
          "predictor_config": {},
          "report_output": "/mnt/workdir/dependency-monkey-210306093513-17a58dbd9d61f188",
          "requirements": "input/Pipfile",
          "requirements_format": "pipenv",
          "runtime_environment": "input/runtime_environment.json",
          "seed": null,
          "stack_output": "http://amun-api-thoth-amun-api-prod.apps.cnv.massopen.cloud/api/v1"
        },
        "thoth-adviser": {
          "metadata": null,
          "verbose": false
        }
      },
      "datetime": "2021-03-06T09:39:16.519294",
      "distribution": {
        "codename": "Ootpa",
        "id": "rhel",
        "like": "fedora",
        "version": "8.3",
        "version_parts": {
          "build_number": "",
          "major": "8",
          "minor": "3"
        }
      },
      "document_id": "dependency-monkey-210306093513-17a58dbd9d61f188",
      "duration": 234,
      "hostname": "dependency-monkey-210306093513-17a58dbd9d61f188-1734411999",
      "os_release": {
        "id": "rhel",
        "name": "Red Hat Enterprise Linux",
        "platform_id": "platform:el8",
        "redhat_bugzilla_product": "Red Hat Enterprise Linux 8",
        "redhat_bugzilla_product_version": "8.3",
        "redhat_support_product": "Red Hat Enterprise Linux",
        "redhat_support_product_version": "8.3",
        "version": "8.3 (Ootpa)",
        "version_id": "8.3"
      },
      "python": {
        "api_version": 1013,
        "implementation_name": "cpython",
        "major": 3,
        "micro": 3,
        "minor": 8,
        "releaselevel": "final",
        "serial": 0
      },
      "thoth_deployment_name": "cnv-prod",
      "timestamp": 1615023556
    },
    "result": {
      "error": false,
      "error_msg": null,
      "parameters": {
        "beam_width": 1000000,
        "context": "input/context.json",
        "count": 1,
        "decision_type": "all",
        "dev": false,
        "dry_run": false,
        "library_usage": null,
        "limit_latest_versions": 9999999,
        "no_pretty": false,
        "pipeline": {
          "boots": [
            {
              "configuration": {
                "package_name": null
              },
              "name": "UbiBoot",
              "unit_run": false
            },
            {
              "configuration": {
                "package_name": null
              },
              "name": "PythonVersionBoot",
              "unit_run": false
            },
            {
              "configuration": {
                "package_name": null
              },
              "name": "RHELVersionBoot",
              "unit_run": false
            },
            {
              "configuration": {
                "default_platform": "linux-x86_64"
              },
              "name": "PlatformBoot",
              "unit_run": false
            },
            {
              "configuration": {
                "package_name": null
              },
              "name": "FullySpecifiedEnvironment",
              "unit_run": false
            }
          ],
          "pseudonyms": [],
          "sieves": [],
          "steps": [],
          "strides": [],
          "wraps": []
        },
        "plot": null,
        "predictor": "RandomWalk",
        "predictor_config": "{}",
        "project": {
          "requirements": {
            "dev-packages": {},
            "packages": {
              "tensorflow": "*"
            },
            "requires": {
              "python_version": "3.8"
            },
            "source": []
          },
          "requirements_locked": null,
          "runtime_environment": {
            "base_image": null,
            "cuda_version": null,
            "cudnn_version": null,
            "hardware": {
              "cpu_family": null,
              "cpu_model": null,
              "gpu_model": null
            },
            "mkl_version": null,
            "name": null,
            "openblas_version": null,
            "openmpi_version": null,
            "operating_system": {
              "name": "rhel",
              "version": "8"
            },
            "platform": null,
            "python_version": "3.8"
          }
        },
        "report_output": "/mnt/workdir/dependency-monkey-210306093513-17a58dbd9d61f188",
        "requirements": "input/Pipfile",
        "requirements_format": "pipenv",
        "runtime_environment": "input/runtime_environment.json",
        "seed": null,
        "stack_output": "http://amun-api-thoth-amun-api-prod.apps.cnv.massopen.cloud/api/v1"
      },
      "report": {
        "responses": [
          {
            "product": {
              "advised_manifest_changes": [],
              "advised_runtime_environment": null,
              "justification": [],
              "project": {
                "requirements": {
                  "dev-packages": {},
                  "packages": {
                    "tensorflow": "*"
                  },
                  "requires": {
                    "python_version": "3.8"
                  },
                  "source": [
                    {
                      "name": "tensorflow-pypi-thoth-station-ninja-index-rhel7-7-AVX2-simple",
                      "url": "https://tensorflow.pypi.thoth-station.ninja/index/rhel7.7/AVX2/simple",
                      "verify_ssl": true
                    }
                  ]
                },
                "requirements_locked": {
                  "_meta": {
                    "hash": {
                      "sha256": "6dbd3b8cf9c2e46d0cadc73f7436d67eafb57b4272316135d542575c5b5a8b9b"
                    },
                    "pipfile-spec": 6,
                    "requires": {
                      "python_version": "3.8"
                    },
                    "sources": [
                      {
                        "name": "tensorflow-pypi-thoth-station-ninja-index-rhel7-7-AVX2-simple",
                        "url": "https://tensorflow.pypi.thoth-station.ninja/index/rhel7.7/AVX2/simple",
                        "verify_ssl": true
                      }
                    ]
                  },
                  "default": {
                    "tensorflow": {
                      "hashes": [],
                      "index": "tensorflow-pypi-thoth-station-ninja-index-rhel7-7-AVX2-simple",
                      "version": "==1.1.0rc1"
                    }
                  },
                  "develop": {}
                },
                "runtime_environment": {
                  "base_image": null,
                  "cuda_version": null,
                  "cudnn_version": null,
                  "hardware": {
                    "cpu_family": null,
                    "cpu_model": null,
                    "gpu_model": null
                  },
                  "mkl_version": null,
                  "name": null,
                  "openblas_version": null,
                  "openmpi_version": null,
                  "operating_system": {
                    "name": "rhel",
                    "version": "8"
                  },
                  "platform": "linux-x86_64",
                  "python_version": "3.8"
                }
              },
              "score": 0
            },
            "response": "inspection-tf-dm-tf24-765f42bb"
          }
        ],
        "skipped": 0
      }
    }
  }
}
